platinumtools/__init__.py
platinumtools/dda_constants.py
platinumtools/dda_models.py
platinumtools/etl_functions.py
platinumtools/help.py
test_scenarios/JobListener.py
test_scenarios/__init__.py
test_scenarios/test_adapters.py
test_scenarios/test_code.py
test_scenarios/test_common_processing.py
test_scenarios/test_enhancement.py
test_scenarios/test_event_normalization.py
test_scenarios/test_guardian.py
test_scenarios/test_helpers.py
test_scenarios/test_scheduling.py
ddaplib-0.0.3.dist-info/LICENSE
ddaplib-0.0.3.dist-info/METADATA
ddaplib-0.0.3.dist-info/WHEEL
ddaplib-0.0.3.dist-info/top_level.txt
ddaplib-0.0.3.dist-info/RECORD
